pybind11/__init__.py
pybind11/__main__.py
pybind11/_version.py
pybind11/commands.py
pybind11/py.typed
pybind11/setup_helpers.py
pybind11/include/pybind11/attr.h
pybind11/include/pybind11/buffer_info.h
pybind11/include/pybind11/cast.h
pybind11/include/pybind11/chrono.h
pybind11/include/pybind11/common.h
pybind11/include/pybind11/complex.h
pybind11/include/pybind11/eigen.h
pybind11/include/pybind11/embed.h
pybind11/include/pybind11/eval.h
pybind11/include/pybind11/functional.h
pybind11/include/pybind11/gil.h
pybind11/include/pybind11/gil_safe_call_once.h
pybind11/include/pybind11/iostream.h
pybind11/include/pybind11/numpy.h
pybind11/include/pybind11/operators.h
pybind11/include/pybind11/options.h
pybind11/include/pybind11/pybind11.h
pybind11/include/pybind11/pytypes.h
pybind11/include/pybind11/stl.h
pybind11/include/pybind11/stl_bind.h
pybind11/include/pybind11/type_caster_pyobject_ptr.h
pybind11/include/pybind11/typing.h
pybind11/include/pybind11/detail/class.h
pybind11/include/pybind11/detail/common.h
pybind11/include/pybind11/detail/descr.h
pybind11/include/pybind11/detail/init.h
pybind11/include/pybind11/detail/internals.h
pybind11/include/pybind11/detail/type_caster_base.h
pybind11/include/pybind11/detail/typeid.h
pybind11/include/pybind11/detail/value_and_holder.h
pybind11/include/pybind11/eigen/common.h
pybind11/include/pybind11/eigen/matrix.h
pybind11/include/pybind11/eigen/tensor.h
pybind11/include/pybind11/stl/filesystem.h
pybind11/share/cmake/pybind11/FindPythonLibsNew.cmake
pybind11/share/cmake/pybind11/pybind11Common.cmake
pybind11/share/cmake/pybind11/pybind11Config.cmake
pybind11/share/cmake/pybind11/pybind11ConfigVersion.cmake
pybind11/share/cmake/pybind11/pybind11GuessPythonExtSuffix.cmake
pybind11/share/cmake/pybind11/pybind11NewTools.cmake
pybind11/share/cmake/pybind11/pybind11Targets.cmake
pybind11/share/cmake/pybind11/pybind11Tools.cmake
pybind11/share/pkgconfig/pybind11.pc
pybind11-2.13.5.dist-info/LICENSE
pybind11-2.13.5.dist-info/METADATA
pybind11-2.13.5.dist-info/WHEEL
pybind11-2.13.5.dist-info/entry_points.txt
pybind11-2.13.5.dist-info/top_level.txt
pybind11-2.13.5.dist-info/RECORD
