Metadata-Version: 2.1
Name: pybind11
Version: 2.13.5
Summary: Seamless operability between C++11 and Python
Home-page: https://github.com/pybind/pybind11
Download-URL: https://github.com/pybind/pybind11/tarball/v2.13.5
Author: Wenzel Jakob
Author-email: wenzel.jakob@epfl.ch
License: BSD
Project-URL: Documentation, https://pybind11.readthedocs.io/
Project-URL: Bug Tracker, https://github.com/pybind/pybind11/issues
Project-URL: Discussions, https://github.com/pybind/pybind11/discussions
Project-URL: Changelog, https://pybind11.readthedocs.io/en/latest/changelog.html
Project-URL: Chat, https://gitter.im/pybind/Lobby
Keywords: C++11,Python bindings
Classifier: Development Status :: 5 - Production/Stable
Classifier: Intended Audience :: Developers
Classifier: Topic :: Software Development :: Libraries :: Python Modules
Classifier: Topic :: Utilities
Classifier: Programming Language :: C++
Classifier: Programming Language :: Python :: 3 :: Only
Classifier: Programming Language :: Python :: 3.7
Classifier: Programming Language :: Python :: 3.8
Classifier: Programming Language :: Python :: 3.9
Classifier: Programming Language :: Python :: 3.10
Classifier: Programming Language :: Python :: 3.11
Classifier: Programming Language :: Python :: 3.12
Classifier: Programming Language :: Python :: 3.13
Classifier: License :: OSI Approved :: BSD License
Classifier: Programming Language :: Python :: Implementation :: PyPy
Classifier: Programming Language :: Python :: Implementation :: CPython
Classifier: Programming Language :: C++
Classifier: Topic :: Software Development :: Libraries :: Python Modules
Requires-Python: >=3.7
License-File: LICENSE
Provides-Extra: global
Requires-Dist: pybind11_global==2.13.5; extra == "global"
